unifiedaiservices/__init__.py
unifiedaiservices/src/_client.py
unifiedaiservices/src/_settings.py
unifiedaiservices-0.2.1.dist-info/METADATA
unifiedaiservices-0.2.1.dist-info/WHEEL
unifiedaiservices-0.2.1.dist-info/top_level.txt
unifiedaiservices-0.2.1.dist-info/RECORD
