Metadata-Version: 2.4
Name: unifiedaiservices
Version: 0.2.1
Summary: Unified Python package for AI models
Author-email: israel <a0534123987@gmail.com>
License: MIT
Requires-Python: >=3.11
Requires-Dist: openai==2.8.1
Requires-Dist: groq==0.36.0
Requires-Dist: google-generativeai>=0.7.0
